make_loc_csv.py
signalkgen/__main__.py
signalkgen/generate.py
signalkgen/move_boats.py
signalkgen-0.2.1.dist-info/LICENSE
signalkgen-0.2.1.dist-info/METADATA
signalkgen-0.2.1.dist-info/WHEEL
signalkgen-0.2.1.dist-info/entry_points.txt
signalkgen-0.2.1.dist-info/top_level.txt
signalkgen-0.2.1.dist-info/RECORD
