Metadata-Version: 2.1
Name: signalkgen
Version: 0.2.1
Summary: JSON generator for Signal K Marine data
Author-email: Ed Sweeney <ed@onextent.com>
License: MIT
Keywords: json,generator,signal-k
Classifier: Programming Language :: Python :: 3
Requires-Python: >=3.11
License-File: LICENSE
